teste_sql70/__init__.py
teste_sql70/modulo1.py
teste_sql70/modulo2.py
teste_sql70/extras/__init__.py
teste_sql70/extras/moduloX1.py
teste_sql70/extras/moduloX2.py
teste_sql70-0.0.2.dist-info/METADATA
teste_sql70-0.0.2.dist-info/WHEEL
teste_sql70-0.0.2.dist-info/top_level.txt
teste_sql70-0.0.2.dist-info/RECORD
