Metadata-Version: 2.1
Name: teste-sql70
Version: 0.0.2
Summary: Mi primer paquete de Python
Home-page: UNKNOWN
Author: Sql 70
Author-email: <sql70@outlook.es>
License: UNKNOWN
Keywords: python,prueba,paquete,teste
Platform: UNKNOWN
Classifier: Development Status :: 3 - Alpha
Classifier: Intended Audience :: Education
Classifier: Programming Language :: Python :: 3
Classifier: Operating System :: Microsoft :: Windows
